{
    "build_hash": "61e4fc37263c3fc201952b609169ad460aae8e58",
    "deleted_api_endpoints": [],
    "deleted_experiments": [],
    "extractor_version": 10,
    "modified_api_endpoints": [],
    "modified_experiments": [],
    "new_api_endpoints": [],
    "new_experiments": [],
    "string_changes": {
        "en": {
            "added": {},
            "deleted": {},
            "modified": {}
        },
        "ko": {
            "added": {},
            "deleted": {},
            "modified": {}
        }
    },
    "timestamp": "2026-05-07T16:53:12.736692+00:00"
}