{
    "build_hash": "89fb123479105000db30ada842791835455ead96",
    "deleted_api_endpoints": [],
    "deleted_experiment_details": [],
    "deleted_experiments": [],
    "extractor_version": 20,
    "modified_api_endpoints": [],
    "modified_experiment_details": [],
    "modified_experiments": [],
    "new_api_endpoints": [],
    "new_experiment_details": [
        {
            "config_keys": [
                "enabled"
            ],
            "default_config": {
                "enabled": false
            },
            "experiment_source": "reference_comment",
            "experiment_type": "apex",
            "id": "2026-07-create-gdm-title",
            "kind": "user",
            "status": "added",
            "timestamp": "2026-07-21T20:40:40Z",
            "treatments": [
                "Variant 1"
            ],
            "variations": {
                "1": {
                    "enabled": true
                }
            }
        }
    ],
    "new_experiments": [
        {
            "config_keys": [
                "enabled"
            ],
            "default_config": {
                "enabled": false
            },
            "experiment_source": "reference_comment",
            "experiment_type": "apex",
            "id": "2026-07-create-gdm-title",
            "kind": "user",
            "timestamp": "2026-07-21T20:40:40Z",
            "treatments": [
                "Variant 1"
            ],
            "variations": {
                "1": {
                    "enabled": true
                }
            }
        },
        {
            "experiment_source": "reference_comment",
            "experiment_type": "apex",
            "id": "2026-07-reduce-leave-call-gpu",
            "kind": "user",
            "timestamp": "2026-07-21T20:43:42Z",
            "treatments": [
                "Variant 1"
            ]
        }
    ],
    "string_changes": {
        "en": {
            "added": {},
            "deleted": {},
            "modified": {}
        },
        "ko": {
            "added": {},
            "deleted": {},
            "modified": {}
        }
    },
    "timestamp": "2026-07-21T20:47:17.710714+00:00"
}