{
    "build_hash": "7e1dacc897d0a9879b394061d038e960d0cb6deb",
    "deleted_api_endpoints": [],
    "deleted_experiment_details": [
        {
            "config_keys": [
                "enabled"
            ],
            "default_config": {
                "enabled": false
            },
            "experiment_source": "self_apex_extraction",
            "experiment_type": "apex",
            "id": "2026-04-quest-heartbeat-executable-fingerprint",
            "kind": "user",
            "status": "deleted",
            "treatments": [
                "Variant 0",
                "Variant 1"
            ],
            "variations": {
                "0": {
                    "enabled": false
                },
                "1": {
                    "enabled": true
                }
            }
        }
    ],
    "deleted_experiments": [
        {
            "config_keys": [
                "enabled"
            ],
            "default_config": {
                "enabled": false
            },
            "experiment_source": "self_apex_extraction",
            "experiment_type": "apex",
            "id": "2026-04-quest-heartbeat-executable-fingerprint",
            "kind": "user",
            "treatments": [
                "Variant 0",
                "Variant 1"
            ],
            "variations": {
                "0": {
                    "enabled": false
                },
                "1": {
                    "enabled": true
                }
            }
        }
    ],
    "extractor_version": 20,
    "modified_api_endpoints": [],
    "modified_experiment_details": [],
    "modified_experiments": [],
    "new_api_endpoints": [],
    "new_experiment_details": [],
    "new_experiments": [],
    "string_changes": {
        "en": {
            "added": {},
            "deleted": {},
            "modified": {}
        },
        "ko": {
            "added": {},
            "deleted": {},
            "modified": {}
        }
    },
    "timestamp": "2026-07-21T17:07:26.575751+00:00"
}