{
    "build_hash": "805fcfcf66e49d0cc7015569ab8aecf132c60504",
    "deleted_api_endpoints": [],
    "deleted_experiment_details": [],
    "deleted_experiments": [],
    "extractor_version": 20,
    "modified_api_endpoints": [],
    "modified_experiment_details": [],
    "modified_experiments": [],
    "new_api_endpoints": [],
    "new_experiment_details": [],
    "new_experiments": [],
    "string_changes": {
        "en": {
            "added": {},
            "deleted": {},
            "modified": {}
        },
        "ko": {
            "added": {},
            "deleted": {},
            "modified": {}
        }
    },
    "timestamp": "2026-07-17T20:03:09.220891+00:00"
}