{
    "build_hash": "91d1b8160f75d4a642f39da3aa5d07c40f72d0f0",
    "deleted_api_endpoints": [],
    "deleted_experiment_details": [],
    "deleted_experiments": [],
    "extractor_version": 20,
    "modified_api_endpoints": [],
    "modified_experiment_details": [],
    "modified_experiments": [],
    "new_api_endpoints": [],
    "new_experiment_details": [],
    "new_experiments": [],
    "string_changes": {
        "en": {
            "added": {},
            "deleted": {},
            "modified": {}
        },
        "ko": {
            "added": {},
            "deleted": {},
            "modified": {}
        }
    },
    "timestamp": "2026-07-08T02:34:42.478062+00:00"
}