{
    "build_hash": "93864b712acb3d3852f89606c3b0ac20401845a1",
    "deleted_api_endpoints": [],
    "deleted_experiment_details": [],
    "deleted_experiments": [],
    "extractor_version": 20,
    "modified_api_endpoints": [],
    "modified_experiment_details": [],
    "modified_experiments": [],
    "new_api_endpoints": [],
    "new_experiment_details": [],
    "new_experiments": [],
    "string_changes": {
        "en": {
            "added": {},
            "deleted": {},
            "modified": {}
        },
        "ko": {
            "added": {},
            "deleted": {},
            "modified": {}
        }
    },
    "timestamp": "2026-07-15T23:53:07.827652+00:00"
}